LICENSE
README.md
pyproject.toml
setup.py
annotation/__init__.py
annotation/admin.py
annotation/apps.py
annotation/models.py
annotation/tests.py
annotation/views.py
annotation/migrations/0001_initial.py
annotation/migrations/0002_remove_author_book_alter_book_author.py
annotation/migrations/__init__.py
example/__init__.py
example/asgi.py
example/settings.py
example/urls.py
example/wsgi.py
queryset_annotations/__init__.py
queryset_annotations/tools.py
queryset_annotations.egg-info/PKG-INFO
queryset_annotations.egg-info/SOURCES.txt
queryset_annotations.egg-info/dependency_links.txt
queryset_annotations.egg-info/requires.txt
queryset_annotations.egg-info/top_level.txt
queryset_annotations/base/__init__.py
queryset_annotations/base/abstract_annotation.py
queryset_annotations/base/context.py
queryset_annotations/base/subquery_annotation.py
queryset_annotations/drf/__init__.py
queryset_annotations/drf/views/__init__.py
queryset_annotations/drf/views/mixins.py
queryset_annotations/mixins/__init__.py
queryset_annotations/mixins/dependency_annotation.py
queryset_annotations/proxy/__init__.py
queryset_annotations/proxy/manager.py
queryset_annotations/proxy/meta.py
queryset_annotations/proxy/model.py