Metadata-Version: 2.1
Name: queryset-annotations
Version: 1.1.0
Summary: Django Smart Queryset Annotations
Home-page: https://github.com/GefMar/django_queryset_annotations
Author: Sergei (Gefest) Romanchuk
License: MIT License
Project-URL: homepage, https://github.com/GefMar/django_queryset_annotations
Classifier: License :: OSI Approved :: MIT License
Requires-Python: >=3.8
License-File: LICENSE
